structcheck/__init__.py
structcheck/__main__.py
structcheck/recscan.py
structcheck/regex.py
structcheck/report.py
structcheck/structcheck.py
structcheck/to_graphviz.py
structcheck/utils.py
structcheck-1.0.41.dist-info/LICENSE
structcheck-1.0.41.dist-info/WHEEL
structcheck-1.0.41.dist-info/METADATA
structcheck-1.0.41.dist-info/RECORD
