Metadata-Version: 2.1
Name: structcheck
Version: 1.0.41
Summary: 
Author: vincentBenet
Author-email: vincent.benet@outlook.fr
Requires-Python: >=3.8,<4.0
Classifier: Programming Language :: Python :: 3
Classifier: Programming Language :: Python :: 3.8
Classifier: Programming Language :: Python :: 3.9
Classifier: Programming Language :: Python :: 3.10
Classifier: Programming Language :: Python :: 3.11
Requires-Dist: graphviz (>=0.20.1,<0.21.0)
